{
  "formatVersion": 1,
  "database": {
    "version": 1,
    "identityHash": "7b361e0a8fc335c17fbc2f5947351bdf",
    "entities": [
      {
        "tableName": "products",
        "createSql": "CREATE TABLE IF NOT EXISTS `${TABLE_NAME}` (`productId` INTEGER PRIMARY KEY AUTOINCREMENT NOT NULL, `productName` TEXT NOT NULL, `quantity` INTEGER NOT NULL)",
        "fields": [
          {
            "fieldPath": "id",
            "columnName": "productId",
            "affinity": "INTEGER",
            "notNull": true
          },
          {
            "fieldPath": "productName",
            "columnName": "productName",
            "affinity": "TEXT",
            "notNull": true
          },
          {
            "fieldPath": "quantity",
            "columnName": "quantity",
            "affinity": "INTEGER",
            "notNull": true
          }
        ],
        "primaryKey": {
          "autoGenerate": true,
          "columnNames": [
            "productId"
          ]
        },
        "indices": [],
        "foreignKeys": []
      }
    ],
    "views": [],
    "setupQueries": [
      "CREATE TABLE IF NOT EXISTS room_master_table (id INTEGER PRIMARY KEY,identity_hash TEXT)",
      "INSERT OR REPLACE INTO room_master_table (id,identity_hash) VALUES(42, '7b361e0a8fc335c17fbc2f5947351bdf')"
    ]
  }
}